problem4-3/problem4-3.v
module xor4 (
    input logic [3:0] a,
    output logic y
);

    assign y = a[0] ^ a[1] ^ a[2] ^ a[3];

endmodule

problem4-3/problem4-3-test.v
module testbench;

    logic [3:0] a;
    logic y;

    xor4 uut (
        .a(a),
        .y(y)
    );

    initial begin
        // Initialize inputs
        a = 4'b0000;
        
        // Delay for 10 time units
        #10;
        $display(a, y);
        
        // Change inputs
        a = 4'b0001;
        
        // Delay for 10 time units
        #10;
        $display(a, y);
        
        // Change inputs
        a = 4'b0011;
        
        // Delay for 10 time units
        #10;
        $display(a, y);
        
        // Change inputs
        a = 4'b0100;
        
        // Delay for 10 time units
        #10;
        $display(a, y);
        
        // Change inputs
        a = 4'b0101;
        
        // Delay for 10 time units
        #10;
        $display(a, y);
        
        // Change inputs
        a = 4'b0110;
        
        // Delay for 10 time units
        #10;
        $display(a, y);
        
        // Change inputs
        a = 4'b0111;
        
        // Delay for 10 time units
        #10;
        $display(a, y);
        
        // Change inputs
        a = 4'b1000;
        
        // Delay for 10 time units
        #10;
        $display(a, y);
        
        // Change inputs
        a = 4'b1001;
        
        // Delay for 10 time units
        #10;
        $display(a, y);
        
        // Change inputs
        a = 4'b1010;
        
        // Delay for 10 time units
        #10;
        $display(a, y);
        
        // Change inputs
        a = 4'b1011;
        
        // Delay for 10 time units
        #10;
        $display(a, y);
        
        // Change inputs
        a = 4'b1100;
        
        // Delay for 10 time units
        #10;
        $display(a, y);
        
        // Change inputs
        a = 4'b1101;
        
        // Delay for 10 time units
        #10;
        $display(a, y);
        
        // Change inputs
        a = 4'b1110;
        
        // Delay for 10 time units
        #10;
        $display(a, y);
        
        // Change inputs
        a = 4'b1111;
        
        // Delay for 10 time units
        #10;
        $display(a, y);

        $finish;
    end

    initial begin
        $dumpfile("problem4-3-test.vcd");
        $dumpvars(0, testbench);
    end
endmodule

problem4-3/problem4-3-test.vcd
$date
	Thu Dec 26 09:05:47 2024
$end
$version
	Icarus Verilog
$end
$timescale
	1s
$end
$scope module testbench $end
$var wire 1 ! y $end
$var reg 4 " a [3:0] $end
$scope module uut $end
$var wire 4 # a [3:0] $end
$var wire 1 ! y $end
$upscope $end
$upscope $end
$enddefinitions $end
$comment Show the parameter values. $end
$dumpall
$end
#0
$dumpvars
b0 #
b0 "
0!
$end
#10
1!
b1 "
b1 #
#20
0!
b11 "
b11 #
#30
1!
b100 "
b100 #
#40
0!
b101 "
b101 #
#50
b110 "
b110 #
#60
1!
b111 "
b111 #
#70
1!
b1000 "
b1000 #
#80
0!
b1001 "
b1001 #
#90
b1010 "
b1010 #
#100
1!
b1011 "
b1011 #
#110
0!
b1100 "
b1100 #
#120
1!
b1101 "
b1101 #
#130
b1110 "
b1110 #
#140
0!
b1111 "
b1111 #
